{
  "year": 2008,
  "mode": "upset_heavy",
  "pretournament_seasons": 23,
  "pretournament_range": "1985\u20132007",
  "predicted_final_four": [
    {
      "name": "T1314",
      "seed": 1
    },
    {
      "name": "T1242",
      "seed": 1
    },
    {
      "name": "T1400",
      "seed": 2
    },
    {
      "name": "T1181",
      "seed": 2
    }
  ],
  "actual_final_four": [
    {
      "name": "T1314",
      "seed": 1
    },
    {
      "name": "T1417",
      "seed": 1
    },
    {
      "name": "T1242",
      "seed": 1
    },
    {
      "name": "T1272",
      "seed": 1
    }
  ],
  "predicted_champion": {
    "name": "T1181",
    "seed": 2
  },
  "actual_champion": {
    "name": "T1242",
    "seed": 1
  },
  "total_correct": 42,
  "total_possible": 63,
  "by_round": {
    "Round of 64": 23,
    "Round of 32": 11,
    "Sweet 16": 5,
    "Elite 8": 2,
    "Final Four": 1,
    "Championship": 0
  },
  "by_round_detail": {
    "Round of 64": {
      "correct": 23,
      "possible": 32
    },
    "Round of 32": {
      "correct": 11,
      "possible": 16
    },
    "Sweet 16": {
      "correct": 5,
      "possible": 8
    },
    "Elite 8": {
      "correct": 2,
      "possible": 4
    },
    "Final Four": {
      "correct": 1,
      "possible": 2
    },
    "Championship": {
      "correct": 0,
      "possible": 1
    }
  },
  "diagnostics": {
    "chalkiness_assessment": "Very chalky: all 4/4 predicted Final Four teams were 1- or 2-seeds. The bracket leaned heavily on chalk.",
    "upset_assessment": "Reasonable upset volume: 13 upsets predicted (historical mean ~15.5, range 9\u201321). Conservative brackets (~11\u201312) tend to outscore balanced ones because wrong upset picks are doubly costly in bracket scoring.",
    "sweet_16_double_digit_review": "Predicted DD seed: T1437 (seed 12) (forced by structure constraint). This team did NOT reach the actual Sweet 16 in 2008.",
    "champion_review": "Champion incorrect: predicted T1181 (seed 2), actual champion was T1242. A seed-2 champion is uncommon but within the historical range."
  },
  "ratings_diagnostics": {
    "season": 2008,
    "source": "historical_team_ratings.csv",
    "matched_by_id": 64,
    "matched_by_name": 0,
    "seed_fallback": 0,
    "total_teams": 64
  }
}